hydronaut/__init__.py
hydronaut/decorator.py
hydronaut/experiment.py
hydronaut/file.py
hydronaut/init.py
hydronaut/log.py
hydronaut/mlflow.py
hydronaut/paths.py
hydronaut/run.py
hydronaut/types.py
hydronaut/version.py
hydronaut/hydra/__init__.py
hydronaut/hydra/config.py
hydronaut/hydra/info.py
hydronaut/hydra/omegaconf.py
hydronaut/hydra/resolvers.py
hydronaut/lightning/experiment.py
hydronaut-2025.1.dist-info/METADATA
hydronaut-2025.1.dist-info/WHEEL
hydronaut-2025.1.dist-info/entry_points.txt
hydronaut-2025.1.dist-info/licenses/LICENSE.txt
hydronaut-2025.1.dist-info/RECORD
