Metadata-Version: 2.4
Name: Hydronaut
Version: 2025.1
Summary: A framework for exploring the depths of hyperparameter space with Hydra and MLflow.
Project-URL: Homepage, https://gitlab.inria.fr/jrye/hydronaut
Project-URL: Source, https://gitlab.inria.fr/jrye/hydronaut.git
Project-URL: Documentation, https://jrye.gitlabpages.inria.fr/hydronaut
Project-URL: Issues, https://gitlab.inria.fr/jrye/hydronaut/issues
Author-email: Jan-Michael Rye <jan-michael.rye@inria.fr>
License: MIT License
License-File: LICENSE.txt
Classifier: License :: OSI Approved :: MIT License
Classifier: Operating System :: OS Independent
Classifier: Programming Language :: Python :: 3
Requires-Python: >=3.6
Requires-Dist: hydra-colorlog
Requires-Dist: hydra-core
Requires-Dist: hydra-joblib-launcher
Requires-Dist: hydra-optuna-sweeper
Requires-Dist: mlflow
Requires-Dist: optuna
Provides-Extra: full
Requires-Dist: lightning; extra == 'full'
Requires-Dist: torch; extra == 'full'
Requires-Dist: torchvision; extra == 'full'
